sdhash/__init__.py
sdhash-0.0.4.dist-info/DESCRIPTION.rst
sdhash-0.0.4.dist-info/METADATA
sdhash-0.0.4.dist-info/metadata.json
sdhash-0.0.4.dist-info/RECORD
sdhash-0.0.4.dist-info/top_level.txt
sdhash-0.0.4.dist-info/WHEEL
