Metadata-Version: 2.0
Name: sdhash
Version: 0.0.4
Summary: Library for image hashing and deduplication.
Home-page: http://github.com/horia141/sdhash
Author: Horia Coman
Author-email: horia141@gmail.com
License: MIT
Keywords: photo image gif hash perceptual dedup deduplication fft
Platform: UNKNOWN
Classifier: Development Status :: 4 - Beta
Classifier: Environment :: Console
Classifier: Intended Audience :: Developers
Classifier: Intended Audience :: Science/Research
Classifier: License :: OSI Approved :: MIT License
Classifier: Operating System :: POSIX
Classifier: Programming Language :: Python :: 2
Classifier: Programming Language :: Python :: 2.6
Classifier: Programming Language :: Python :: 2.7
Classifier: Topic :: Multimedia :: Graphics
Classifier: Topic :: Multimedia :: Video
Classifier: Topic :: Scientific/Engineering :: Image Recognition
Classifier: Topic :: Scientific/Engineering :: Information Analysis
Classifier: Topic :: Software Development :: Libraries :: Python Modules
Requires-Dist: pillow
Requires-Dist: numpy
Requires-Dist: scipy
